factorycore_utils/__init__.py
factorycore_utils/azure_function_helpers.py
factorycore_utils/catalog_helpers.py
factorycore_utils/dataframe_helpers.py
factorycore_utils/dataframe_validator.py
factorycore_utils/dbutils_helper.py
factorycore_utils/extensions/__init__.py
factorycore_utils/extensions/column_ext.py
factorycore_utils/extensions/dataframe_ext.py
factorycore_utils/extensions/spark_session_ext.py
factorycore_utils/functions.py
factorycore_utils/model_registry_helpers.py
factorycore_utils/search_helpers.py
factorycore_utils/sql_statement_helpers.py
factorycore_utils/string_helpers.py
factorycore_utils/transformations.py
factorycore_utils-4.1.15.dist-info/METADATA
factorycore_utils-4.1.15.dist-info/WHEEL
factorycore_utils-4.1.15.dist-info/RECORD
